stackdiff/__init__.py
stackdiff/__main__.py
stackdiff/cli.py
stackdiff/py.typed
stackdiff/stack_diff.py
stackdiff/version/VERSION
stackdiff/version/__init__.py
stackdiff/version/py.typed
stackdiff-1.1.0.dist-info/LICENSE
stackdiff-1.1.0.dist-info/METADATA
stackdiff-1.1.0.dist-info/WHEEL
stackdiff-1.1.0.dist-info/entry_points.txt
stackdiff-1.1.0.dist-info/top_level.txt
stackdiff-1.1.0.dist-info/RECORD
