Metadata-Version: 2.1
Name: stackdiff
Version: 1.1.0
Summary: Visualises the changes described by an Amazon Web Services CloudFormation stack change set
Home-page: https://github.com/cariad/stackdiff
Author: Cariad Eccleston
Author-email: cariad@cariad.earth
License: MIT
Platform: UNKNOWN
Classifier: Development Status :: 5 - Production/Stable
Classifier: Environment :: Console
Classifier: License :: OSI Approved :: MIT License
Classifier: Natural Language :: English
Classifier: Programming Language :: Python :: 3 :: Only
Classifier: Programming Language :: Python :: 3.10
Classifier: Programming Language :: Python :: 3.8
Classifier: Programming Language :: Python :: 3.9
Classifier: Topic :: Utilities
Classifier: Typing :: Typed
Requires-Python: >=3.8
License-File: LICENSE
Requires-Dist: ansiscape (<2.0,>=1.1)
Requires-Dist: boto3 (<2.0,>=1.18)
Requires-Dist: differently (<2.0,>=1.0.1)
Requires-Dist: pyyaml (<7.0,>=6.0)
Requires-Dist: tabulate (<1.0,>=0.8)
